{
  "fbst": {
    "last_success_utc": "2026-05-11T15:35:39.901810+00:00"
  },
  "gcal": {
    "last_success_utc": "2026-05-11T18:00:50.778115+00:00"
  },
  "goodreads": {
    "last_success_utc": "2026-05-11T15:35:39.512113+00:00"
  },
  "goodreads-reading": {
    "last_success_utc": "2026-05-11T15:35:38.505638+00:00"
  },
  "mlb": {
    "last_success_utc": "2026-05-11T15:35:38.077454+00:00"
  },
  "plex": {
    "last_success_utc": "2026-05-11T15:48:03.917530+00:00"
  },
  "projects": {
    "last_success_utc": "2026-05-11T19:44:37.019096+00:00"
  },
  "spotify": {
    "last_success_utc": "2026-05-11T18:15:30.563450+00:00"
  },
  "whoop": {
    "last_success_utc": "2026-05-11T12:43:30.674221+00:00"
  }
}