{
  "fbst": {
    "last_success_utc": "2026-06-20T19:56:41.859016+00:00"
  },
  "gcal": {
    "last_success_utc": "2026-06-20T20:17:51.009524+00:00"
  },
  "goodreads": {
    "last_success_utc": "2026-06-20T19:56:41.526117+00:00"
  },
  "goodreads-reading": {
    "last_success_utc": "2026-06-20T19:56:39.830999+00:00"
  },
  "mlb": {
    "last_success_utc": "2026-06-20T19:56:39.336736+00:00"
  },
  "plex": {
    "last_success_utc": "2026-06-20T20:06:26.517722+00:00"
  },
  "project-docs": {
    "last_success_utc": "2026-06-20T15:11:39.659482+00:00"
  },
  "project-docs:aleph-roadmap": {
    "last_success_utc": "2026-06-20T15:11:38.772088+00:00"
  },
  "project-docs:fantastic-leagues-roadmap": {
    "last_success_utc": "2026-06-20T15:11:39.151600+00:00"
  },
  "project-docs:judge-tool-roadmap": {
    "last_success_utc": "2026-06-20T15:11:39.659235+00:00"
  },
  "projects": {
    "last_success_utc": "2026-06-20T15:01:40.330078+00:00"
  },
  "spotify": {
    "last_success_utc": "2026-06-20T22:00:33.047858+00:00"
  },
  "whoop": {
    "last_success_utc": "2026-06-20T12:02:30.405736+00:00"
  }
}