{
  "fbst": {
    "last_success_utc": "2026-06-25T09:44:11.718222+00:00"
  },
  "gcal": {
    "last_success_utc": "2026-06-25T09:28:07.202618+00:00"
  },
  "goodreads": {
    "last_success_utc": "2026-06-25T09:44:11.532812+00:00"
  },
  "goodreads-reading": {
    "last_success_utc": "2026-06-25T09:44:09.650508+00:00"
  },
  "mlb": {
    "last_success_utc": "2026-06-25T09:44:09.197708+00:00"
  },
  "plex": {
    "last_success_utc": "2026-06-25T04:50:15.561381+00:00"
  },
  "project-docs": {
    "last_success_utc": "2026-06-24T15:38:01.669515+00:00"
  },
  "project-docs:aleph-roadmap": {
    "last_success_utc": "2026-06-24T15:38:01.103498+00:00"
  },
  "project-docs:fantastic-leagues-changelog": {
    "last_success_utc": "2026-06-24T15:38:01.259914+00:00"
  },
  "project-docs:fantastic-leagues-roadmap": {
    "last_success_utc": "2026-06-24T15:38:01.395639+00:00"
  },
  "project-docs:judge-tool-roadmap": {
    "last_success_utc": "2026-06-24T15:38:01.662715+00:00"
  },
  "projects": {
    "last_success_utc": "2026-06-25T07:00:45.158157+00:00"
  },
  "spotify": {
    "last_success_utc": "2026-06-25T08:17:51.550152+00:00"
  },
  "whoop": {
    "last_success_utc": "2026-06-24T12:23:10.877034+00:00"
  }
}